tornado_replay/__init__.py
tornado_replay/base.py
tornado_replay/handler.py
tornado_replay/models.py
tornado_replay/queue.py
tornado_replay/statics/inspect.js
tornado_replay/statics/dependency/bootstrap.min.css
tornado_replay/statics/dependency/bootstrap.min.js
tornado_replay/statics/dependency/jquery1.11.1.min.js
tornado_replay/statics/dependency/popper.min.js
tornado_replay/statics/pretty_json/backbone.min.js
tornado_replay/statics/pretty_json/pretty_json.css
tornado_replay/statics/pretty_json/pretty_json.js
tornado_replay/statics/pretty_json/underscore.min.js
tornado_replay/templates/base.html
tornado_replay/templates/index.html
tornado_replay/templates/record_detail_template.html
tornado_replay/templates/record_template.html
tornado_replay-0.1.3.dist-info/METADATA
tornado_replay-0.1.3.dist-info/WHEEL
tornado_replay-0.1.3.dist-info/top_level.txt
tornado_replay-0.1.3.dist-info/RECORD
